{
  "name": "Targets!Sonic",
  "location": "",
  "seriesID": 11,
  "fileName": "/GrTSn.dat",
  "additionalFiles": [],
  "soundBank": 55,
  "reverbValue1": 1,
  "reverbValue2": 1,
  "collisionMaterials": 2151411416,
  "mapDescPointer": 4294967295,
  "onStageInit": 2149726312,
  "onStageLoad": 2149726424,
  "onStageGo": 2149726428,
  "onGo": 2149726308,
  "onUnknown2": 2149726464,
  "onTouchLine": 2149727032,
  "onUnknown4": 2149727040,
  "unknownValue": 1,
  "movingCollisionPointer": 0,
  "movingCollisionCount": 0,
  "items": [],
  "playlist": {
    "entries": []
  },
  "assets": {
    "icon": null,
    "banner": null
  }
}